easywebview/__init__.py
easywebview/__main__.py
easywebview/cli.py
easywebview/default_page.py
easywebview/profiles.py
easywebview/py.typed
easywebview-0.1.1.dist-info/METADATA
easywebview-0.1.1.dist-info/WHEEL
easywebview-0.1.1.dist-info/entry_points.txt
easywebview-0.1.1.dist-info/licenses/LICENSE
easywebview-0.1.1.dist-info/RECORD
