Metadata-Version: 2.4
Name: easywebview
Version: 0.1.1
Summary: A tiny standalone WebView window powered by pywebview.
License: MIT License
License-File: LICENSE
Keywords: browser,pywebview,webview
Classifier: License :: OSI Approved :: MIT License
Classifier: Programming Language :: Python :: 3
Classifier: Programming Language :: Python :: 3 :: Only
Classifier: Programming Language :: Python :: 3.10
Classifier: Programming Language :: Python :: 3.11
Classifier: Programming Language :: Python :: 3.12
Classifier: Programming Language :: Python :: 3.13
Requires-Python: >=3.10
Requires-Dist: pywebview>=6.1
Provides-Extra: cef
Requires-Dist: pywebview[cef]>=6.1; extra == 'cef'
Provides-Extra: dev
Requires-Dist: build>=1.3.0; extra == 'dev'
Requires-Dist: twine>=6.2.0; extra == 'dev'
Provides-Extra: gtk
Requires-Dist: pywebview[gtk]>=6.1; extra == 'gtk'
Provides-Extra: qt
Requires-Dist: pywebview[qt]>=6.1; extra == 'qt'
Provides-Extra: ssl
Requires-Dist: pywebview[ssl]>=6.1; extra == 'ssl'
